greyout/__init__.py
greyout/command_line.py
greyout-0.0.5.dist-info/METADATA
greyout-0.0.5.dist-info/WHEEL
greyout-0.0.5.dist-info/entry_points.txt
greyout-0.0.5.dist-info/top_level.txt
greyout-0.0.5.dist-info/RECORD
